{'postID': 51365013, 'title': '【原创】最近体重上升   但是我绝对没有偷吃', 'detail': '只是把你放进了我的心里', 'images': ['http://cdn.u1.huluxia.com/g4/M03/BC/0F/rBAAdmM6m8OAY8ckAAF-eoxmOps080.jpg'], 'score': 5, 'scoreTxt': '', 'hit': 193, 'commentCount': 10, 'notice': 0, 'weight': 0, 'isGood': 0, 'createTime': 1664785353000, 'activeTime': 1664787480000, 'line': 0, 'user': {'userID': 30086076, 'nick': '拒绝ˡ₀ᵛₑ', 'avatar': 'http://cdn.u1.huluxia.com/g4/M01/82/0B/rBAAdmL_cV-ACQjjAAEoTOE7GgY082.jpg', 'gender': 1, 'age': 18, 'role': 0, 'experience': 6900, 'credits': 20887, 'identityTitle': '接待组长', 'identityColor': 4278190334, 'level': 4, 'levelColor': 0, 'integral': 0, 'uuid': 0, 'integralNick': '初入门槛', 'signature': None, 'medalList': None, 'nickColor': None, 'nightNickColor': None, 'userRemark': None, 'ipAddr': None}, 'ext': None, 'category': None, 'tagid': 5601, 'status': 0, 'praise': 2, 'voice': '{"height":606.0,"imgfid":"g4/M03/BC/0F/rBAAdmM6m8OAY8ckAAF-eoxmOps080.jpg","length":"18","videoSize":3772672.0,"videofid":"qiniu/30086076/1664785347671/5649445f3332302d3138302d33302d31303030303030302d32332d313636343738353037313231362e6d7034","width":1078.0,"imghost":"http://cdn.u1.huluxia.com/","videohost":"http://video.ksyun.huluxia.net/"}', 'isAuthention': 0, 'isRich': 0, 'appOrientation': 0, 'isAppPost': 0, 'appVersion': None, 'appSize': 0.0, 'appSystem': None, 'appLogo': None, 'screenshots': None, 'appIntroduce': None, 'appUrl': None, 'appLanguage': None, 'isGif': 0, 'isTop': 0, 'state': 0}